ttkSimpleDialog/__init__.py
ttkSimpleDialog/ttkSimpleDialog.py
ttkSimpleDialog-1.2.1.data/scripts/runner
ttkSimpleDialog-1.2.1.dist-info/LICENSE
ttkSimpleDialog-1.2.1.dist-info/METADATA
ttkSimpleDialog-1.2.1.dist-info/WHEEL
ttkSimpleDialog-1.2.1.dist-info/top_level.txt
ttkSimpleDialog-1.2.1.dist-info/RECORD
