Metadata-Version: 1.1
Name: ttkSimpleDialog
Version: 1.2.1
Summary: ttk themed version of ttkSimpleDialog
Home-page: https://github.com/TDHolmes/ttkSimpleDialog
Author: Tyler Holmes
Author-email: tyler@holmesengineering.com
License: UNKNOWN
Platform: UNKNOWN
Classifier: Development Status :: 5 - Production/Stable
Classifier: Environment :: Plugins
Classifier: Intended Audience :: Developers
Classifier: License :: Freely Distributable
Classifier: Operating System :: OS Independent
Classifier: Programming Language :: Python
Classifier: Natural Language :: English
Classifier: Topic :: Software Development :: User Interfaces
